apollinaire/.gitkeep
apollinaire/__init__.py
apollinaire/peakbagging/__init__.py
apollinaire/peakbagging/a2z_manipulations.py
apollinaire/peakbagging/a2z_no_pandas.py
apollinaire/peakbagging/ampl_mode.py
apollinaire/peakbagging/analyse_window.py
apollinaire/peakbagging/background.py
apollinaire/peakbagging/banana_diagram.py
apollinaire/peakbagging/bayesian.py
apollinaire/peakbagging/chain_reader.py
apollinaire/peakbagging/fit_tools.py
apollinaire/peakbagging/global_pattern.py
apollinaire/peakbagging/header.py
apollinaire/peakbagging/likelihood.py
apollinaire/peakbagging/mode_selection.py
apollinaire/peakbagging/modified_optimize.py
apollinaire/peakbagging/peakbagging.py
apollinaire/peakbagging/psd_preprocessing.py
apollinaire/peakbagging/quality_assurance.py
apollinaire/peakbagging/regressor.py
apollinaire/peakbagging/rotation.py
apollinaire/peakbagging/save_chain.py
apollinaire/peakbagging/stellar_framework.py
apollinaire/peakbagging/templates/__init__.py
apollinaire/peakbagging/templates/apollinaire
apollinaire/peakbagging/templates/input_golf.a2z
apollinaire/peakbagging/templates/input_saxo.a2z
apollinaire/peakbagging/templates/kepler_epsilon.csv
apollinaire/peakbagging/templates/saxo_param_back.txt
apollinaire/peakbagging/templates/saxo_pkb.txt
apollinaire/peakbagging/templates/test.a2z
apollinaire/peakbagging/templates/verif.pkb
apollinaire/peakbagging/templates/zone.txt
apollinaire/peakbagging/test_data/.DS_Store
apollinaire/peakbagging/test_data/__init__.py
apollinaire/peakbagging/test_data/mcmc_background.dat
apollinaire/peakbagging/test_data/mcmc_background.h5
apollinaire/peakbagging/test_data/mcmc_pattern.dat
apollinaire/peakbagging/test_data/mcmc_pattern.h5
apollinaire/peakbagging/test_data/mcmc_sampler_order_19.dat
apollinaire/peakbagging/test_data/mcmc_sampler_order_19.h5
apollinaire/peakbagging/test_data/mcmc_sampler_order_20.dat
apollinaire/peakbagging/test_data/mcmc_sampler_order_20.h5
apollinaire/peakbagging/test_data/mcmc_sampler_order_21.dat
apollinaire-1.3.2.dist-info/licenses/LICENSE
apollinaire-1.3.2.dist-info/METADATA
apollinaire-1.3.2.dist-info/WHEEL
apollinaire-1.3.2.dist-info/top_level.txt
apollinaire-1.3.2.dist-info/RECORD
