Metadata-Version: 2.4
Name: apollinaire
Version: 1.3.2
Summary: Module for helio- and asteroseismic data analysis.
Author-email: "Sylvain N. Breton" <sylvain.breton@inaf.it>
License: 
Project-URL: Homepage, https://gitlab.com/sybreton/apollinaire
Project-URL: Documentation, https://apollinaire.readthedocs.io/en/latest/index.html
Keywords: stellar physics,asteroseismology,helioseismology,bayesian,peakbagging,mcmc,data,data_analysis
Classifier: Programming Language :: Python :: 3
Classifier: License :: OSI Approved :: CEA CNRS Inria Logiciel Libre License, version 2.1 (CeCILL-2.1)
Classifier: Operating System :: OS Independent
Requires-Python: >=3.7
License-File: LICENSE
Requires-Dist: numpy
Requires-Dist: pandas
Requires-Dist: matplotlib
Requires-Dist: statsmodels
Requires-Dist: emcee
Requires-Dist: dill
Requires-Dist: pathos
Requires-Dist: corner
Requires-Dist: h5py
Requires-Dist: scipy
Requires-Dist: numba
Requires-Dist: george
Requires-Dist: astropy
Requires-Dist: tqdm
Dynamic: license-file
